strig/__init__.py
strig/constants.py
strig/types.py
strig/functions/__init__.py
strig/functions/alpha.py
strig/functions/alphanumeric.py
strig/functions/numeric.py
strig/functions/password.py
strig/functions/urlsafe.py
strig/functions/var.py
strig/functions/var_methods/__init__.py
strig/functions/var_methods/dates.py
strig/functions/var_methods/system.py
strig-2.0.0.dist-info/LICENSE
strig-2.0.0.dist-info/METADATA
strig-2.0.0.dist-info/WHEEL
strig-2.0.0.dist-info/top_level.txt
strig-2.0.0.dist-info/RECORD
