Metadata-Version: 2.1
Name: strig
Version: 2.0.0
Summary: A simple and intuitive Python package for generating random strings and numbers. 
Home-page: https://github.com/w-kuipers/strig
Author: Wibo Kuipers
Author-email: wkuipersoss@gmail.com
Project-URL: Bug Tracker, https://github.com/w-kuipers/strig/issues
Classifier: Programming Language :: Python :: 3
Classifier: License :: OSI Approved :: MIT License
Classifier: Operating System :: OS Independent
Requires-Python: >=3.7
License-File: LICENSE
